hivehoney/__init__.py
hivehoney/hh.py
hivehoney/query.sql
hivehoney-1.0.4.dist-info/LICENSE
hivehoney-1.0.4.dist-info/WHEEL
hivehoney-1.0.4.dist-info/METADATA
hivehoney-1.0.4.dist-info/RECORD
