Metadata-Version: 2.1
Name: hivehoney
Version: 1.0.4
Summary: Client-less data retrieval from Hive.
Home-page: https://github.com/hive-scripts/hivehoney
License: UNKNOWN
Author: Alex Buzunov
Author-email: alex_buz@icloud.com
Classifier: License :: OSI Approved :: MIT License
